gasp/__about__.py
gasp/__init__.py
gasp/analysis.py
gasp/coil.py
gasp/core.py
gasp/dataloader.py
gasp/dataset.py
gasp/gasp.py
gasp/path.py
gasp/phantom.py
gasp/responses.py
gasp/sampling.py
gasp/simulation.py
gasp/ssfp.py
gasp/tissue.py
gasp/view.py
gasp_ssfp-0.0.3.dist-info/METADATA
gasp_ssfp-0.0.3.dist-info/WHEEL
gasp_ssfp-0.0.3.dist-info/RECORD
