Metadata-Version: 2.4
Name: gasp-ssfp
Version: 0.0.3
Summary: Generation of Arbitary Spectral Profiles using bSSFp MRI
Project-URL: Homepage, https://github.com/michaelmendoza/gasp
Project-URL: Bug Tracker, https://github.com/michaelmendoza/gasp/issues
Author-email: Michael Mendoza <askmichaelmendoza@gmail.com>
Keywords: gasp,mri,ssfp
Classifier: Programming Language :: Python :: 3
Requires-Python: >=3.8
Requires-Dist: gdown
Requires-Dist: jupyterlab
Requires-Dist: matplotlib
Requires-Dist: numpy
Requires-Dist: pymapvbvd
Requires-Dist: scikit-image
Requires-Dist: scipy
Requires-Dist: seaborn
